{
    "id": "zaqqWja2",
    "rated": true,
    "variant": "standard",
    "speed": "rapid",
    "perf": "rapid",
    "createdAt": "2022-10-31 16:22:32.473000+00:00",
    "lastMoveAt": "2022-10-31 16:49:49.440000+00:00",
    "status": "resign",
    "players": {
        "white": {
            "user": {
                "name": "ChadiBen",
                "id": "chadiben"
            },
            "rating": 1779,
            "ratingDiff": -5,
            "analysis": {
                "inaccuracy": 14,
                "mistake": 4,
                "blunder": 6,
                "acpl": 64
            }
        },
        "black": {
            "user": {
                "name": "Quidam81",
                "id": "quidam81"
            },
            "rating": 1784,
            "ratingDiff": 5,
            "analysis": {
                "inaccuracy": 9,
                "mistake": 3,
                "blunder": 7,
                "acpl": 53
            }
        }
    },
    "winner": "black",
    "opening": {
        "eco": "A40",
        "name": "Englund Gambit",
        "ply": 2
    },
    "moves": "d4 e5 dxe5 Bc5 Nf3 Ne7 Bf4 O-O e3 Qe8 Bc4 Nbc6 O-O Bb6 Nc3 Ng6 Bg3 Ncxe5 Nxe5 Nxe5 Bb3 c6 Qd6 Ng6 Rad1 Bd8 Ne2 Be7 Qd3 d5 Nd4 Bc5 Ne2 f5 Nf4 Nxf4 Bxf4 Bb6 c4 dxc4 Bxc4+ Kh8 Bd6 Rf6 Qc3 Be6 Bxe6 Qxe6 Be5 Rg6 Rd6 Qf7 Rxg6 Qxg6 Rd1 Qf7 a4 Re8 Bf4 Bc7 Bxc7 Qxc7 Qd3 h6 Qd7 Qxd7 Rxd7 Rb8 Kf1 Kh7 Ke2 Kg6 Kf3 Kf6 Kf4 g5+ Kg3 h5 f4 h4+ Kf3 g4+ Kf2 Ke6 Rg7 a6 g3 h3 Ke2 b5 Rg6+ Kd5 axb5 Rxb5 Kf1 Rxb2 Kg1 a5 Rf6 Ke4 Rxc6 Kxe3 Rc3+ Kd4 Ra3 Rb5 Kf2 Kc4 Ra2 Kb3 Ra1 Rd5 Ke3 a4 Rb1+ Kc2 Ra1 Rd3+ Kf2 a3 Ra2+ Kb1 Re2 a2 Rxa2 Kxa2 Ke2 Rf3",
    "analysis": [
        {
            "eval": 0
        },
        {
            "eval": 174,
            "best": "g8f6",
            "variation": "Nf6 c4 e6 Nf3 d5 cxd5 exd5 Bf4 c6 Nc3",
            "judgment": {
                "name": "Blunder",
                "comment": "Blunder. Nf6 was best."
            }
        },
        {
            "eval": 167
        },
        {
            "eval": 163
        },
        {
            "eval": 186
        },
        {
            "eval": 248
        },
        {
            "eval": 162,
            "best": "a2a3",
            "variation": "a3 O-O b4 Bb6 Bb2 a5 Nbd2 axb4 axb4 Rxa1",
            "judgment": {
                "name": "Inaccuracy",
                "comment": "Inaccuracy. a3 was best."
            }
        },
        {
            "eval": 155
        },
        {
            "eval": 136
        },
        {
            "eval": 265,
            "best": "e7g6",
            "variation": "Ng6 Bg3 Nc6 Bd3 Re8 Bxg6 hxg6 Nc3 d6 exd6",
            "judgment": {
                "name": "Mistake",
                "comment": "Mistake. Ng6 was best."
            }
        },
        {
            "eval": 180,
            "best": "f1d3",
            "variation": "Bd3 h6",
            "judgment": {
                "name": "Inaccuracy",
                "comment": "Inaccuracy. Bd3 was best."
            }
        },
        {
            "eval": 222
        },
        {
            "eval": 153,
            "best": "c4d3",
            "variation": "Bd3",
            "judgment": {
                "name": "Inaccuracy",
                "comment": "Inaccuracy. Bd3 was best."
            }
        },
        {
            "eval": 265,
            "best": "e7g6",
            "variation": "Ng6 Qd5 b6 Bd3 Bb7 Bxg6 hxg6 Nc3 Nd8 Qc4 Qe6 Qe2 Bb4 Nb5",
            "judgment": {
                "name": "Inaccuracy",
                "comment": "Inaccuracy. Ng6 was best."
            }
        },
        {
            "eval": 227
        },
        {
            "eval": 344
        },
        {
            "eval": 80,
            "best": "a2a4",
            "variation": "a4 Ncxe5 Nxe5 Nxe5 a5 Bxa5 Rxa5 Nxc4 Rc5 Nxb2 Qd4 c6 Ne4 d5",
            "judgment": {
                "name": "Blunder",
                "comment": "Blunder. a4 was best."
            }
        },
        {
            "eval": 87
        },
        {
            "eval": 70
        },
        {
            "eval": 118
        },
        {
            "eval": 79
        },
        {
            "eval": 291,
            "best": "d7d6",
            "variation": "d6 a4",
            "judgment": {
                "name": "Blunder",
                "comment": "Blunder. d6 was best."
            }
        },
        {
            "eval": 204,
            "best": "f2f4",
            "variation": "f4 Ng6",
            "judgment": {
                "name": "Inaccuracy",
                "comment": "Inaccuracy. f4 was best."
            }
        },
        {
            "eval": 232
        },
        {
            "eval": 179
        },
        {
            "eval": 211
        },
        {
            "eval": 82,
            "best": "e3e4",
            "variation": "e4 Be7 Qd2 b5 Rfe1 a5 a4 Bb4 axb5 a4 Ba2 Qe7 Bd6 Qxd6",
            "judgment": {
                "name": "Mistake",
                "comment": "Mistake. e4 was best."
            }
        },
        {
            "eval": 111
        },
        {
            "eval": 105
        },
        {
            "eval": 105
        },
        {
            "eval": -208,
            "best": "c2c4",
            "variation": "c4 dxc4 Bxc4 Bf6 Qc2 Ne5 Bb3 Be6 Nc3 Bxb3 Qxb3 Qe6 Qxb7 Rfb8",
            "judgment": {
                "name": "Blunder",
                "comment": "Blunder. c4 was best."
            }
        },
        {
            "eval": 87,
            "best": "c6c5",
            "variation": "c5 Nb5",
            "judgment": {
                "name": "Blunder",
                "comment": "Blunder. c5 was best."
            }
        },
        {
            "eval": 0,
            "best": "c2c3",
            "variation": "c3 Qe7 h3 Bd6 Bxd6 Qxd6 f4 Qe7 c4 dxc4 Bxc4 Bd7 e4 Rad8",
            "judgment": {
                "name": "Inaccuracy",
                "comment": "Inaccuracy. c3 was best."
            }
        },
        {
            "eval": 300,
            "best": "g6e5",
            "variation": "Ne5 Qc3 Nd7 Qd3",
            "judgment": {
                "name": "Blunder",
                "comment": "Blunder. Ne5 was best."
            }
        },
        {
            "eval": 17,
            "best": "c2c4",
            "variation": "c4 Be6",
            "judgment": {
                "name": "Blunder",
                "comment": "Blunder. c4 was best."
            }
        },
        {
            "eval": 19
        },
        {
            "eval": 6
        },
        {
            "eval": 199,
            "best": "c8e6",
            "variation": "Be6",
            "judgment": {
                "name": "Blunder",
                "comment": "Blunder. Be6 was best."
            }
        },
        {
            "eval": 196
        },
        {
            "eval": 238
        },
        {
            "eval": 12,
            "best": "d3c4",
            "variation": "Qxc4+ Kh8",
            "judgment": {
                "name": "Blunder",
                "comment": "Blunder. Qxc4+ was best."
            }
        },
        {
            "eval": 191,
            "best": "c8e6",
            "variation": "Be6",
            "judgment": {
                "name": "Blunder",
                "comment": "Blunder. Be6 was best."
            }
        },
        {
            "eval": 109,
            "best": "d3b3",
            "variation": "Qb3 h6",
            "judgment": {
                "name": "Inaccuracy",
                "comment": "Inaccuracy. Qb3 was best."
            }
        },
        {
            "eval": 126
        },
        {
            "eval": 85
        },
        {
            "eval": 100
        },
        {
            "eval": 103
        },
        {
            "eval": 52
        },
        {
            "eval": 62
        },
        {
            "eval": 119,
            "best": "f6f7",
            "variation": "Rf7 a4",
            "judgment": {
                "name": "Inaccuracy",
                "comment": "Inaccuracy. Rf7 was best."
            }
        },
        {
            "eval": 59,
            "best": "a2a4",
            "variation": "a4",
            "judgment": {
                "name": "Inaccuracy",
                "comment": "Inaccuracy. a4 was best."
            }
        },
        {
            "eval": 119,
            "best": "e6e7",
            "variation": "Qe7 Rd3",
            "judgment": {
                "name": "Inaccuracy",
                "comment": "Inaccuracy. Qe7 was best."
            }
        },
        {
            "eval": 3,
            "best": "d6d3",
            "variation": "Rd3",
            "judgment": {
                "name": "Mistake",
                "comment": "Mistake. Rd3 was best."
            }
        },
        {
            "eval": 70,
            "best": "h7g6",
            "variation": "hxg6 a4 Rd8 a5 Bc7 a6 Bxe5 Qxe5 bxa6 Qg3 Rd2 h3 Kh7 Ra1",
            "judgment": {
                "name": "Inaccuracy",
                "comment": "Inaccuracy. hxg6 was best."
            }
        },
        {
            "eval": 59
        },
        {
            "eval": 79
        },
        {
            "eval": 71
        },
        {
            "eval": 96
        },
        {
            "eval": 37,
            "best": "d1d3",
            "variation": "Rd3",
            "judgment": {
                "name": "Inaccuracy",
                "comment": "Inaccuracy. Rd3 was best."
            }
        },
        {
            "eval": 52
        },
        {
            "eval": 50
        },
        {
            "eval": 52
        },
        {
            "eval": 65
        },
        {
            "eval": 129,
            "best": "c7f7",
            "variation": "Qf7 g3 h6 h4 Kh7 Qd7 Re7 Qd8 Qb3 Rd4 Re5 Rd7 Rd5 Rxd5",
            "judgment": {
                "name": "Inaccuracy",
                "comment": "Inaccuracy. Qf7 was best."
            }
        },
        {
            "eval": 13,
            "best": "d3f5",
            "variation": "Qxf5",
            "judgment": {
                "name": "Mistake",
                "comment": "Mistake. Qxf5 was best."
            }
        },
        {
            "eval": 13
        },
        {
            "eval": 13
        },
        {
            "eval": 85,
            "best": "e8e4",
            "variation": "Re4",
            "judgment": {
                "name": "Inaccuracy",
                "comment": "Inaccuracy. Re4 was best."
            }
        },
        {
            "eval": 90
        },
        {
            "eval": 172,
            "best": "a7a5",
            "variation": "a5 b3 Kh7 g3 Kg6 h4 h5 Ke2 Kh6 Rc7 g6 Kf3 b5 Ra7",
            "judgment": {
                "name": "Inaccuracy",
                "comment": "Inaccuracy. a5 was best."
            }
        },
        {
            "eval": 93,
            "best": "b2b4",
            "variation": "b4 a5 bxa5 Kg8 Ke2 Ra8 Rxb7 Rxa5 Rb4 Kf7 Rc4 c5 Kd3 Ke6",
            "judgment": {
                "name": "Inaccuracy",
                "comment": "Inaccuracy. b4 was best."
            }
        },
        {
            "eval": 220,
            "best": "a7a5",
            "variation": "a5",
            "judgment": {
                "name": "Mistake",
                "comment": "Mistake. a5 was best."
            }
        },
        {
            "eval": 50,
            "best": "a4a5",
            "variation": "a5 Kf6 b4 h5 Kd3 g5 Kd4 g4 h4 Ke6 Rh7 Rd8+ Kc3 Rd1",
            "judgment": {
                "name": "Mistake",
                "comment": "Mistake. a5 was best."
            }
        },
        {
            "eval": 121,
            "best": "a7a5",
            "variation": "a5",
            "judgment": {
                "name": "Inaccuracy",
                "comment": "Inaccuracy. a5 was best."
            }
        },
        {
            "eval": 20,
            "best": "a4a5",
            "variation": "a5 a6 Rc7 g5 g4 Kg6 h3 h5 Kg3 fxg4 hxg4 h4+ Kg2 Kf6",
            "judgment": {
                "name": "Inaccuracy",
                "comment": "Inaccuracy. a5 was best."
            }
        },
        {
            "eval": 33
        },
        {
            "eval": 16
        },
        {
            "eval": 55
        },
        {
            "eval": 10
        },
        {
            "eval": 17
        },
        {
            "eval": 0
        },
        {
            "eval": 0
        },
        {
            "eval": -13
        },
        {
            "eval": 0
        },
        {
            "eval": -57,
            "best": "d7h7",
            "variation": "Rh7 Kd5 Rxh4 b5 Rh5 Ke4 a5 Rd8 Ke2 Rd3 Rh7 Rxe3+ Kd2 Rb3",
            "judgment": {
                "name": "Inaccuracy",
                "comment": "Inaccuracy. Rh7 was best."
            }
        },
        {
            "eval": 16,
            "best": "a7a5",
            "variation": "a5 e4 b5 Rg6+ Ke7 Rxc6 bxa4 Rc2 Rb3 exf5 Kf6 Ke2 Kxf5 Rc5+",
            "judgment": {
                "name": "Inaccuracy",
                "comment": "Inaccuracy. a5 was best."
            }
        },
        {
            "eval": 0
        },
        {
            "eval": 16
        },
        {
            "eval": 0
        },
        {
            "eval": 0
        },
        {
            "eval": -364,
            "best": "a4a5",
            "variation": "a5 Re8 Ra7 Kd6 Rxa6 Re4 Kd3 Rb4 Kc2 Re4 Kd3",
            "judgment": {
                "name": "Blunder",
                "comment": "Blunder. a5 was best."
            }
        },
        {
            "eval": -82,
            "best": "e6f7",
            "variation": "Kf7 Rxc6 bxa4 Rc2 Rb3 Kf2 a5 Re2 Kf6 Kf1 a3 bxa3 Rxa3 e4",
            "judgment": {
                "name": "Blunder",
                "comment": "Blunder. Kf7 was best."
            }
        },
        {
            "eval": -470,
            "best": "a4a5",
            "variation": "a5 Ra8 e4+ Kxe4 Rxc6 Kd5 Rc1 b4 Kd3 Kd6 Rc2 Rb8 Kc4 Rb5",
            "judgment": {
                "name": "Blunder",
                "comment": "Blunder. a5 was best."
            }
        },
        {
            "eval": -542
        },
        {
            "eval": -887,
            "best": "e2d3",
            "variation": "Kd3 Rxb2 Rg5 Rxh2 Rxf5+ Kd6 Rf6+ Kc5 Rf5+ Kb4 Rf8 Rf2 Rb8+ Kc5",
            "judgment": {
                "name": "Inaccuracy",
                "comment": "Inaccuracy. Kd3 was best."
            }
        },
        {
            "eval": -1019
        },
        {
            "eval": -1011
        },
        {
            "eval": -1089
        },
        {
            "eval": -1425
        },
        {
            "eval": -1197
        },
        {
            "eval": -2108
        },
        {
            "eval": -1303
        },
        {
            "mate": -10,
            "best": "c6e6",
            "variation": "Re6+ Kf3 Re1 Rb3 Kf1 a4 Ra1 a3 Ke1 Kg2 Kd1 Kxh2 Kc2 Rf3",
            "judgment": {
                "name": "Inaccuracy",
                "comment": "Checkmate is now unavoidable. Re6+ was best."
            }
        },
        {
            "eval": -875,
            "best": "e3e2",
            "variation": "Ke2 Rc1 a4 Rf1 a3 Rf2+ Ke3 Rf1 a2 Re1+ Kf3 Rf1+ Ke2 Rf2+",
            "judgment": {
                "name": "Mistake",
                "comment": "Lost forced checkmate sequence. Ke2 was best."
            }
        },
        {
            "eval": -884
        },
        {
            "eval": -816
        },
        {
            "eval": -866
        },
        {
            "eval": -877
        },
        {
            "eval": -880
        },
        {
            "eval": -924
        },
        {
            "eval": -937
        },
        {
            "eval": -910
        },
        {
            "eval": -1044
        },
        {
            "eval": -1105
        },
        {
            "eval": -1067
        },
        {
            "eval": -1052
        },
        {
            "eval": -1280
        },
        {
            "eval": -1127
        },
        {
            "eval": -1365
        },
        {
            "eval": -1378
        },
        {
            "eval": -1397
        },
        {
            "eval": -1628
        },
        {
            "eval": -1447
        },
        {
            "eval": -1437
        },
        {
            "mate": -8,
            "best": "e2e1",
            "variation": "Re1+ Kb2 Re2+ Kb3 Re1 Rd2+ Ke3 Rxh2 Kd4 Kb2 Ke5 a1=Q Rxa1 Kxa1",
            "judgment": {
                "name": "Inaccuracy",
                "comment": "Checkmate is now unavoidable. Re1+ was best."
            }
        },
        {
            "mate": -7
        },
        {
            "mate": -12
        },
        {
            "mate": -6
        }
    ],
    "clock": {
        "initial": 600,
        "increment": 5,
        "totalTime": 800
    }
}