{
    "id": "BG5nUjUM",
    "rated": true,
    "variant": "standard",
    "speed": "rapid",
    "perf": "rapid",
    "createdAt": "2022-11-08 20:09:20.596000+00:00",
    "lastMoveAt": "2022-11-08 20:23:04.605000+00:00",
    "status": "outoftime",
    "players": {
        "white": {
            "user": {
                "name": "Jye24",
                "id": "jye24"
            },
            "rating": 1504,
            "ratingDiff": 6,
            "analysis": {
                "inaccuracy": 4,
                "mistake": 3,
                "blunder": 4,
                "acpl": 71
            }
        },
        "black": {
            "user": {
                "name": "nachmaninov",
                "id": "nachmaninov"
            },
            "rating": 1515,
            "ratingDiff": -5,
            "analysis": {
                "inaccuracy": 6,
                "mistake": 1,
                "blunder": 5,
                "acpl": 91
            }
        }
    },
    "winner": "white",
    "opening": {
        "eco": "C02",
        "name": "French Defense: Advance Variation, Euwe Variation",
        "ply": 10
    },
    "moves": "e4 e6 d4 d5 e5 c5 c3 Nc6 Nf3 Bd7 Bg5 f6 Bh4 g5 Bg3 fxe5 Bxe5 Nxe5 Nxe5 Nf6 Nd2 Qe7 Ndf3 O-O-O Nxg5 Be8 Qb3 Nd7 Nxd7 Bxd7 Nf3 c4 Qc2 Bg7 b3 cxb3 Qxb3 a6 Rb1 Bc6 c4 dxc4 Qxc4 Bxd4 Nxd4 Rxd4 Qxd4 Rd8 Qg4 Qd6 Be2 Qd2+ Kf1 Qxa2 Rc1 Qd2 Rd1 Qa5 Qxe6+ Kc7 Rxd8 Kxd8 Qf6+ Kc7 Bf3",
    "analysis": [
        {
            "eval": 36
        },
        {
            "eval": 0
        },
        {
            "eval": 30
        },
        {
            "eval": 25
        },
        {
            "eval": 0
        },
        {
            "eval": 30
        },
        {
            "eval": 30
        },
        {
            "eval": 0
        },
        {
            "eval": 0
        },
        {
            "eval": 25
        },
        {
            "eval": -95,
            "best": "f1e2",
            "variation": "Be2 Rc8 O-O cxd4 cxd4 Nge7 Na3 Nf5 Nc2 Qb6",
            "judgment": {
                "name": "Mistake",
                "comment": "Mistake. Be2 was best."
            }
        },
        {
            "eval": -56
        },
        {
            "eval": -149,
            "best": "e5f6",
            "variation": "exf6 Nxf6 Nbd2 Qb6 Qb3 cxd4 Qxb6 axb6 Nxd4 Bc5",
            "judgment": {
                "name": "Inaccuracy",
                "comment": "Inaccuracy. exf6 was best."
            }
        },
        {
            "eval": 321,
            "best": "d8b6",
            "variation": "Qb6 exf6 Nxf6 Qb3 cxd4 Qxb6 axb6 Bb5 Bc5 Bxc6 bxc6 cxd4 Bb4+ Nbd2",
            "judgment": {
                "name": "Blunder",
                "comment": "Blunder. Qb6 was best."
            }
        },
        {
            "eval": -145,
            "best": "f3g5",
            "variation": "Nxg5 Qb6",
            "judgment": {
                "name": "Blunder",
                "comment": "Blunder. Nxg5 was best."
            }
        },
        {
            "eval": 179,
            "best": "g5g4",
            "variation": "g4 Nfd2 h5 h3 fxe5 dxe5 h4 hxg4 Bg7 Bh2 Bxe5 f4 Bc7 Na3",
            "judgment": {
                "name": "Blunder",
                "comment": "Blunder. g4 was best."
            }
        },
        {
            "eval": -41,
            "best": "f3e5",
            "variation": "Nxe5 Nf6 Be2 Nxe5 dxe5 Ne4 Bh5+ Ke7 Nd2 Nxg3 fxg3 Qc7 O-O Kd8",
            "judgment": {
                "name": "Blunder",
                "comment": "Blunder. Nxe5 was best."
            }
        },
        {
            "eval": 72,
            "best": "g8f6",
            "variation": "Nf6 Bg3 Qb6 Nbd2 Qxb2 Be2 g4 Ne5 Bh6 Rc1 cxd4 Rc2 Qa3 O-O",
            "judgment": {
                "name": "Mistake",
                "comment": "Mistake. Nf6 was best."
            }
        },
        {
            "eval": 40
        },
        {
            "eval": 55
        },
        {
            "eval": 11
        },
        {
            "eval": 104,
            "best": "c5d4",
            "variation": "cxd4 cxd4",
            "judgment": {
                "name": "Inaccuracy",
                "comment": "Inaccuracy. cxd4 was best."
            }
        },
        {
            "eval": -15,
            "best": "d4c5",
            "variation": "dxc5 Qxc5 Bd3 Qc7 Qe2 Ba4 Nef3 O-O-O Nd4 Re8 Bb5 Bxb5 Nxb5 Qb6",
            "judgment": {
                "name": "Mistake",
                "comment": "Mistake. dxc5 was best."
            }
        },
        {
            "eval": 84,
            "best": "g5g4",
            "variation": "g4 Ng5",
            "judgment": {
                "name": "Inaccuracy",
                "comment": "Inaccuracy. g4 was best."
            }
        },
        {
            "eval": 83
        },
        {
            "eval": 89
        },
        {
            "eval": 9,
            "best": "g5f3",
            "variation": "Ngf3",
            "judgment": {
                "name": "Inaccuracy",
                "comment": "Inaccuracy. Ngf3 was best."
            }
        },
        {
            "eval": 21
        },
        {
            "eval": -58,
            "best": "g5f3",
            "variation": "Ngf3 Nxe5 Nxe5 Bg7 Be2 Bxe5 dxe5 Qg7 O-O Rg8 g3 Qxe5 Rfe1 Qd6",
            "judgment": {
                "name": "Inaccuracy",
                "comment": "Inaccuracy. Ngf3 was best."
            }
        },
        {
            "eval": 10,
            "best": "e7g5",
            "variation": "Qxg5",
            "judgment": {
                "name": "Inaccuracy",
                "comment": "Inaccuracy. Qxg5 was best."
            }
        },
        {
            "eval": 51
        },
        {
            "eval": 109,
            "best": "c8b8",
            "variation": "Kb8 Ne5 Qg7 O-O-O Bd6 Nxd7+ Rxd7 dxc5 Bxc5 f3 h5 Qc2 Rg8 Kb1",
            "judgment": {
                "name": "Inaccuracy",
                "comment": "Inaccuracy. Kb8 was best."
            }
        },
        {
            "eval": 148
        },
        {
            "eval": 143
        },
        {
            "eval": -26,
            "best": "f1e2",
            "variation": "Be2 Be8",
            "judgment": {
                "name": "Blunder",
                "comment": "Blunder. Be2 was best."
            }
        },
        {
            "eval": 55,
            "best": "e6e5",
            "variation": "e5",
            "judgment": {
                "name": "Inaccuracy",
                "comment": "Inaccuracy. e5 was best."
            }
        },
        {
            "eval": -59,
            "best": "a2b3",
            "variation": "axb3 e5",
            "judgment": {
                "name": "Mistake",
                "comment": "Mistake. axb3 was best."
            }
        },
        {
            "eval": 205,
            "best": "e6e5",
            "variation": "e5",
            "judgment": {
                "name": "Blunder",
                "comment": "Blunder. e5 was best."
            }
        },
        {
            "eval": 215
        },
        {
            "eval": 213
        },
        {
            "eval": -176,
            "best": "f1e2",
            "variation": "Be2 e5",
            "judgment": {
                "name": "Blunder",
                "comment": "Blunder. Be2 was best."
            }
        },
        {
            "eval": 57,
            "best": "e6e5",
            "variation": "e5",
            "judgment": {
                "name": "Blunder",
                "comment": "Blunder. e5 was best."
            }
        },
        {
            "eval": -5,
            "best": "f1c4",
            "variation": "Bxc4",
            "judgment": {
                "name": "Inaccuracy",
                "comment": "Inaccuracy. Bxc4 was best."
            }
        },
        {
            "eval": 416,
            "best": "e7c7",
            "variation": "Qc7 Bd3",
            "judgment": {
                "name": "Blunder",
                "comment": "Blunder. Qc7 was best."
            }
        },
        {
            "eval": 428
        },
        {
            "eval": 678,
            "best": "e7d6",
            "variation": "Qd6 Nf3 Rhg8 Be2 Rxg2 Rd1 Qf8 Rg1 Rxg1+ Nxg1 Kb8 Rxd8+ Qxd8 Qc3",
            "judgment": {
                "name": "Inaccuracy",
                "comment": "Inaccuracy. Qd6 was best."
            }
        },
        {
            "eval": 688
        },
        {
            "eval": 758
        },
        {
            "eval": 609
        },
        {
            "eval": 613
        },
        {
            "eval": 617
        },
        {
            "eval": 609
        },
        {
            "eval": 607
        },
        {
            "eval": 605
        },
        {
            "eval": 580
        },
        {
            "eval": 667
        },
        {
            "eval": 651
        },
        {
            "eval": 702
        },
        {
            "eval": 708
        },
        {
            "eval": 801
        },
        {
            "eval": 823
        },
        {
            "eval": 749
        },
        {
            "eval": 740
        },
        {
            "eval": 740
        },
        {
            "eval": 602
        }
    ],
    "clock": {
        "initial": 600,
        "increment": 0,
        "totalTime": 600
    }
}