{
    "id": "q4uNwmmP",
    "rated": true,
    "variant": "standard",
    "speed": "rapid",
    "perf": "rapid",
    "createdAt": "2022-09-14 05:55:58.969000+00:00",
    "lastMoveAt": "2022-09-14 06:15:00.843000+00:00",
    "status": "outoftime",
    "players": {
        "white": {
            "user": {
                "name": "N4A",
                "id": "n4a"
            },
            "rating": 1556,
            "ratingDiff": -6,
            "analysis": {
                "inaccuracy": 6,
                "mistake": 1,
                "blunder": 3,
                "acpl": 70
            }
        },
        "black": {
            "user": {
                "name": "hjindal",
                "id": "hjindal"
            },
            "rating": 1538,
            "ratingDiff": 6,
            "analysis": {
                "inaccuracy": 8,
                "mistake": 1,
                "blunder": 3,
                "acpl": 88
            }
        }
    },
    "winner": "black",
    "opening": {
        "eco": "C20",
        "name": "King's Pawn Game: Leonardis Variation",
        "ply": 3
    },
    "moves": "e4 e5 d3 Nc6 Be3 d6 c3 f5 Nd2 f4 Bxf4 exf4 Ngf3 Bg4 Be2 Bxf3 Bxf3 Qf6 O-O Ne5 Re1 Nxf3+ Nxf3 O-O-O e5 dxe5 Rxe5 Bd6 Ra5 Kb8 Qa4 a6 Qb3 Ne7 Rxa6 Nc6 Rxc6 Kc8 Rc4 Rhe8 Qa4 Bf8 Qa8+ Kd7 Qxb7 Rc8 Qc6+ Qxc6 Ne5+ Kd6 Nxc6 g5 Nd4 g4 Nf5+ Ke6 Nd4+ Ke5 Nc6+ Kf5 g3 fxg3 hxg3 Re1+ Rxe1 Ra8 Re5+ Kg6 Rxg4+ Kf6 Rf4+ Kg6 Re6+ Kg5 Re5+ Kg6 Rg4+ Kf6 Rgg5 Bd6 Ref5+ Ke6 Nd4+ Kd7 Rf7+ Kc8 Rg8+ Kb7 Rxa8 Kxa8 Rf8+ Kb7 Rf5 Kb6 Rb5+ Ka7 a4 Ka6 b4 c5 bxc5 Bxc5 Nc6 Bf8",
    "analysis": [
        {
            "eval": 0
        },
        {
            "eval": 12
        },
        {
            "eval": 0
        },
        {
            "eval": -9
        },
        {
            "eval": -22
        },
        {
            "eval": 27
        },
        {
            "eval": -25
        },
        {
            "eval": -3
        },
        {
            "eval": -295,
            "best": "e4f5",
            "variation": "exf5 Bxf5 d4 Nf6 d5 Ne7 c4 Bg6 Bd3 Nf5",
            "judgment": {
                "name": "Blunder",
                "comment": "Blunder. exf5 was best."
            }
        },
        {
            "eval": -293
        },
        {
            "eval": -299
        },
        {
            "eval": -278
        },
        {
            "eval": -312
        },
        {
            "eval": -207,
            "best": "d8e7",
            "variation": "Qe7 Qb3 Nf6 d4 Bd7 Qxb7 Rb8 Qa6 Nxe4 O-O-O Rb6 Qc4 Nxd2 Rxd2",
            "judgment": {
                "name": "Inaccuracy",
                "comment": "Inaccuracy. Qe7 was best."
            }
        },
        {
            "eval": -275,
            "best": "d1b3",
            "variation": "Qb3 Be7 d4 Nh6 O-O-O Nf7 g3 O-O gxf4 Na5 Qa4 c5 dxc5 dxc5",
            "judgment": {
                "name": "Inaccuracy",
                "comment": "Inaccuracy. Qb3 was best."
            }
        },
        {
            "eval": -176,
            "best": "d8e7",
            "variation": "Qe7 d4",
            "judgment": {
                "name": "Inaccuracy",
                "comment": "Inaccuracy. Qe7 was best."
            }
        },
        {
            "eval": -277,
            "best": "d2f3",
            "variation": "Nxf3 Qe7",
            "judgment": {
                "name": "Inaccuracy",
                "comment": "Inaccuracy. Nxf3 was best."
            }
        },
        {
            "eval": -163,
            "best": "c6e5",
            "variation": "Ne5 Be2 c6 d4 Nf7 Bc4 Ngh6 Bb3 Be7 Qe2 Qc7 O-O-O O-O-O Qf3",
            "judgment": {
                "name": "Inaccuracy",
                "comment": "Inaccuracy. Ne5 was best."
            }
        },
        {
            "eval": -257,
            "best": "d3d4",
            "variation": "d4",
            "judgment": {
                "name": "Inaccuracy",
                "comment": "Inaccuracy. d4 was best."
            }
        },
        {
            "eval": -73,
            "best": "g8h6",
            "variation": "Nh6 d4 Be7 Qa4 Kf8 Rfe1 Nf7 Bg4 h5 Bd7 g5 Bxc6 bxc6 Qxc6",
            "judgment": {
                "name": "Blunder",
                "comment": "Blunder. Nh6 was best."
            }
        },
        {
            "eval": -196,
            "best": "d1a4",
            "variation": "Qa4+ Kd8 d4 Nxf3+ Nxf3 Qe6 Rfe1 Qd7 Qb3 Kc8 c4 a5 e5 Ra6",
            "judgment": {
                "name": "Mistake",
                "comment": "Mistake. Qa4+ was best."
            }
        },
        {
            "eval": -217
        },
        {
            "eval": -205
        },
        {
            "eval": -190
        },
        {
            "eval": -409,
            "best": "a2a4",
            "variation": "a4",
            "judgment": {
                "name": "Blunder",
                "comment": "Blunder. a4 was best."
            }
        },
        {
            "eval": -401
        },
        {
            "eval": -462
        },
        {
            "eval": -436
        },
        {
            "eval": -483
        },
        {
            "eval": -354,
            "best": "a7a6",
            "variation": "a6 d4 Ne7 b4 Nc6 Ra4 Rhe8 Qb3 Na7 Ra5 c6 a4 Bc7 Rh5",
            "judgment": {
                "name": "Inaccuracy",
                "comment": "Inaccuracy. a6 was best."
            }
        },
        {
            "eval": -381
        },
        {
            "eval": -339
        },
        {
            "eval": -364
        },
        {
            "eval": -250,
            "best": "b8c8",
            "variation": "Kc8 Re1 Ne7 Re6 Qf8 Qc4 c6 h4 Rd7 Ne5 Bxe5 Raxe5 Nd5 Rxc6+",
            "judgment": {
                "name": "Inaccuracy",
                "comment": "Inaccuracy. Kc8 was best."
            }
        },
        {
            "eval": -287
        },
        {
            "eval": 397,
            "best": "f6f5",
            "variation": "Qf5",
            "judgment": {
                "name": "Blunder",
                "comment": "Blunder. Qf5 was best."
            }
        },
        {
            "eval": 375
        },
        {
            "eval": 439
        },
        {
            "eval": 420
        },
        {
            "eval": 448
        },
        {
            "eval": 428
        },
        {
            "eval": 768,
            "best": "c8b8",
            "variation": "Kb8 Re4 Rxe4 Qxe4 g5 Qxh7 Rh8 Qd7 Qg6 h3 Qxd3 Re1 Qc2 Qg7",
            "judgment": {
                "name": "Mistake",
                "comment": "Mistake. Kb8 was best."
            }
        },
        {
            "eval": 771
        },
        {
            "eval": 806
        },
        {
            "eval": 812
        },
        {
            "eval": 874
        },
        {
            "eval": -627,
            "best": "h2h3",
            "variation": "h3 Bd6 Qc6+ Ke7 a4 g5 Re4+ Kf8 Rxe8+ Rxe8 a5 h5 a6 g4",
            "judgment": {
                "name": "Blunder",
                "comment": "Blunder. h3 was best."
            }
        },
        {
            "eval": -611
        },
        {
            "eval": -937,
            "best": "c4c6",
            "variation": "Rxc6 Kxc6 b4 Kb7 a4 Re2 c4 Rce8 h3 Rc2 a5 Rc3 b5 Rxd3",
            "judgment": {
                "name": "Inaccuracy",
                "comment": "Inaccuracy. Rxc6 was best."
            }
        },
        {
            "eval": 588,
            "best": "e8e5",
            "variation": "Rxe5 Rxc6 Kxc6 Kf1 Re7 Re1 Kd7 Rxe7+ Bxe7 Ke2 Ra8 a4 Rxa4 Kd1",
            "judgment": {
                "name": "Blunder",
                "comment": "Blunder. Rxe5 was best."
            }
        },
        {
            "eval": 603
        },
        {
            "eval": 680
        },
        {
            "eval": 658
        },
        {
            "eval": 684
        },
        {
            "eval": 619
        },
        {
            "eval": 820
        },
        {
            "eval": 635
        },
        {
            "eval": 725
        },
        {
            "eval": 593
        },
        {
            "eval": 659
        },
        {
            "eval": 630
        },
        {
            "eval": 712
        },
        {
            "eval": 756
        },
        {
            "eval": 1279
        },
        {
            "eval": 1295
        },
        {
            "eval": 1528
        },
        {
            "eval": 1321
        },
        {
            "eval": 1350
        },
        {
            "eval": 1350
        },
        {
            "eval": 1392
        },
        {
            "eval": 1322
        },
        {
            "eval": 1471
        },
        {
            "eval": 1427
        },
        {
            "mate": 3,
            "best": "g6g7",
            "variation": "Kg7 a4 Kg8 Ne5 Bg7 a5 c5 Kg2 h6 b4 cxb4 cxb4 h5 Rh4",
            "judgment": {
                "name": "Inaccuracy",
                "comment": "Checkmate is now unavoidable. Kg7 was best."
            }
        },
        {
            "eval": 1400,
            "best": "c6d4",
            "variation": "Nd4 Bg7 Nf3+ Kh5 g4#",
            "judgment": {
                "name": "Inaccuracy",
                "comment": "Lost forced checkmate sequence. Nd4 was best."
            }
        },
        {
            "eval": 1403
        },
        {
            "eval": 1386
        },
        {
            "eval": 1393
        },
        {
            "eval": 1402
        },
        {
            "eval": 5950
        },
        {
            "eval": 2253
        },
        {
            "eval": 5607
        },
        {
            "eval": 5603
        },
        {
            "eval": 5569
        },
        {
            "eval": 1933
        },
        {
            "eval": 2449
        },
        {
            "eval": 1976
        },
        {
            "eval": 2001
        },
        {
            "eval": 1831
        },
        {
            "eval": 5861
        },
        {
            "eval": 886
        },
        {
            "eval": 1634
        },
        {
            "eval": 1674
        },
        {
            "eval": 1688
        },
        {
            "eval": 1705
        },
        {
            "eval": 3705
        },
        {
            "eval": 1769
        },
        {
            "eval": 1826
        },
        {
            "eval": 1944
        },
        {
            "mate": 11,
            "best": "h7h6",
            "variation": "h6 Ne6 Ka7 f4 Ka6 Rh5 Kb6 Rxh6 Kc6 g4 Kb6 Rh7 Kc6 g5",
            "judgment": {
                "name": "Inaccuracy",
                "comment": "Checkmate is now unavoidable. h6 was best."
            }
        },
        {
            "mate": 9
        },
        {
            "mate": 9
        },
        {
            "eval": 6523,
            "best": "b5c5",
            "variation": "Rxc5 Kb6 Rh5 h6 Rxh6+ Kc7 Rh7+ Kb6 f4 Kc5 Rh6 Kd5 Ra6 Kc5",
            "judgment": {
                "name": "Inaccuracy",
                "comment": "Lost forced checkmate sequence. Rxc5 was best."
            }
        },
        {
            "mate": 10,
            "best": "c5b6",
            "variation": "Bb6 Nb4+ Ka7 d4 h6 f4 h5 a5 Bc7 Rxh5 Ka8 a6 Bb8 Nc6",
            "judgment": {
                "name": "Inaccuracy",
                "comment": "Checkmate is now unavoidable. Bb6 was best."
            }
        }
    ],
    "clock": {
        "initial": 600,
        "increment": 0,
        "totalTime": 600
    }
}