{
    "id": "LwWW9WzT",
    "rated": true,
    "variant": "standard",
    "speed": "rapid",
    "perf": "rapid",
    "createdAt": "2022-10-27 11:33:30.866000+00:00",
    "lastMoveAt": "2022-10-27 11:39:06.937000+00:00",
    "status": "mate",
    "players": {
        "white": {
            "user": {
                "name": "IliaMamykin",
                "id": "iliamamykin"
            },
            "rating": 1335,
            "ratingDiff": -5,
            "analysis": {
                "inaccuracy": 5,
                "mistake": 6,
                "blunder": 3,
                "acpl": 117
            }
        },
        "black": {
            "user": {
                "name": "Diske2Cis",
                "id": "diske2cis"
            },
            "rating": 1341,
            "ratingDiff": 7,
            "analysis": {
                "inaccuracy": 4,
                "mistake": 6,
                "blunder": 3,
                "acpl": 89
            }
        }
    },
    "winner": "black",
    "opening": {
        "eco": "B21",
        "name": "Sicilian Defense: McDonnell Attack",
        "ply": 3
    },
    "moves": "e4 c5 f4 Nc6 e5 d6 d3 Bf5 Be3 f6 exf6 Nxf6 Be2 g6 d4 Bg7 dxc5 O-O c3 Ne4 cxd6 Qxd6 Bc4+ Kh8 Nf3 Qxd1+ Kxd1 Rad8+ Ke2 Bg4 Na3 Bxf3+ gxf3 Nf6 Nb5 a6 Nc7 b5 Ne6 bxc4 Nxf8 Rxf8 Rad1 e5 fxe5 Nxe5 Rd2 Re8 Rhd1 Nd3 b3 Bh6 bxc4 Nf4+ Kf2 Nh3+ Kg3 Bxe3 Rd3 Ng5 Kh4 Nxf3+ Kg3 Ng5 h4 Nh5+ Kg4 Re4#",
    "analysis": [
        {
            "eval": 0
        },
        {
            "eval": 32
        },
        {
            "eval": 0
        },
        {
            "eval": 5
        },
        {
            "eval": -83,
            "best": "g1f3",
            "variation": "Nf3 e6 Bb5 Nd4 Nxd4 cxd4 O-O a6 Be2 Bc5",
            "judgment": {
                "name": "Inaccuracy",
                "comment": "Inaccuracy. Nf3 was best."
            }
        },
        {
            "eval": -52
        },
        {
            "eval": -210,
            "best": "g1f3",
            "variation": "Nf3 g6 Bb5 Bd7 Qe2 Bg7 O-O dxe5 Bxc6 Bxc6",
            "judgment": {
                "name": "Mistake",
                "comment": "Mistake. Nf3 was best."
            }
        },
        {
            "eval": -119,
            "best": "d6e5",
            "variation": "dxe5 fxe5 Nxe5 Nf3 Nc6 Be2 Nf6 O-O Bg4 h3",
            "judgment": {
                "name": "Inaccuracy",
                "comment": "Inaccuracy. dxe5 was best."
            }
        },
        {
            "eval": -135
        },
        {
            "eval": -75,
            "best": "d6e5",
            "variation": "dxe5 fxe5",
            "judgment": {
                "name": "Inaccuracy",
                "comment": "Inaccuracy. dxe5 was best."
            }
        },
        {
            "eval": -87
        },
        {
            "eval": -73
        },
        {
            "eval": -116
        },
        {
            "eval": -95
        },
        {
            "eval": -420,
            "best": "e2f3",
            "variation": "Bf3 Qb6",
            "judgment": {
                "name": "Blunder",
                "comment": "Blunder. Bf3 was best."
            }
        },
        {
            "eval": -262,
            "best": "d8b6",
            "variation": "Qb6 Nf3 Qxb2 Nbd2 Qc3 Bf2 Bxc2 Qc1 cxd4 Bb5 d3 O-O Bg7 Rb1",
            "judgment": {
                "name": "Mistake",
                "comment": "Mistake. Qb6 was best."
            }
        },
        {
            "eval": -277
        },
        {
            "eval": -131,
            "best": "d6c5",
            "variation": "dxc5 c3 Qxd1+ Bxd1 Nd5 Bc1 e5 Nh3 Bxh3 gxh3 exf4 O-O Rf8 Na3",
            "judgment": {
                "name": "Mistake",
                "comment": "Mistake. dxc5 was best."
            }
        },
        {
            "eval": -129
        },
        {
            "eval": 0,
            "best": "e7e5",
            "variation": "e5 Nf3",
            "judgment": {
                "name": "Mistake",
                "comment": "Mistake. e5 was best."
            }
        },
        {
            "eval": -93,
            "best": "g1f3",
            "variation": "Nf3 e5 cxd6 exf4 Bxf4 g5 Qd5+ Kh8 Nbd2 Qb6 Nxe4 gxf4 Neg5 Qxb2",
            "judgment": {
                "name": "Inaccuracy",
                "comment": "Inaccuracy. Nf3 was best."
            }
        },
        {
            "eval": 72,
            "best": "e7d6",
            "variation": "exd6 Bc4+",
            "judgment": {
                "name": "Blunder",
                "comment": "Blunder. exd6 was best."
            }
        },
        {
            "eval": -85,
            "best": "g1f3",
            "variation": "Nf3 Rad8 O-O Qc7 Qe1 e5 fxe5 Nxe5 Nd4 Rfe8 Nd2 Ng4 Bxg4 Bxg4",
            "judgment": {
                "name": "Mistake",
                "comment": "Mistake. Nf3 was best."
            }
        },
        {
            "eval": -90
        },
        {
            "eval": -121
        },
        {
            "eval": -127
        },
        {
            "eval": -137
        },
        {
            "eval": -72,
            "best": "e7e5",
            "variation": "e5 fxe5 Nxe5 Nxe5 Bxe5 Nd2 Rad8 Kc1 Nxd2 Bxd2 Be4 Re1 Rf2 Rxe4",
            "judgment": {
                "name": "Inaccuracy",
                "comment": "Inaccuracy. e5 was best."
            }
        },
        {
            "eval": -73
        },
        {
            "eval": 0,
            "best": "e7e5",
            "variation": "e5 Rd1",
            "judgment": {
                "name": "Inaccuracy",
                "comment": "Inaccuracy. e5 was best."
            }
        },
        {
            "eval": -77,
            "best": "h1d1",
            "variation": "Rd1 Rxd1 Kxd1 e5 Bb5 exf4 Bxc6 Rd8+ Ke1 bxc6 Bxa7 Re8 Kf1 Rd8",
            "judgment": {
                "name": "Inaccuracy",
                "comment": "Inaccuracy. Rd1 was best."
            }
        },
        {
            "eval": 60,
            "best": "e7e5",
            "variation": "e5 Rhd1 Rxd1 Rxd1 exf4 Bc1 Bxc3 bxc3 Nxc3+ Ke1 Nxd1 Kxd1 Kg7 Nb5",
            "judgment": {
                "name": "Mistake",
                "comment": "Mistake. e5 was best."
            }
        },
        {
            "eval": 26
        },
        {
            "eval": 163,
            "best": "e4d6",
            "variation": "Nd6",
            "judgment": {
                "name": "Mistake",
                "comment": "Mistake. Nd6 was best."
            }
        },
        {
            "eval": 40,
            "best": "a1d1",
            "variation": "Rad1 Bh6 Rxd8 Rxd8 Rd1 Rxd1 Kxd1 Nh5 Bd5 Bxf4 Bg1 a6 Be6 b5",
            "judgment": {
                "name": "Mistake",
                "comment": "Mistake. Rad1 was best."
            }
        },
        {
            "eval": 50
        },
        {
            "eval": 57
        },
        {
            "eval": 373,
            "best": "c6a5",
            "variation": "Na5 Bb3 Rd6 Rad1 Nxb3 axb3 Rc8 Rxd6 exd6 Bb6 Bh6 f5 Kg8 fxg6",
            "judgment": {
                "name": "Blunder",
                "comment": "Blunder. Na5 was best."
            }
        },
        {
            "eval": -298,
            "best": "c4b3",
            "variation": "Bb3 Rb8",
            "judgment": {
                "name": "Blunder",
                "comment": "Blunder. Bb3 was best."
            }
        },
        {
            "eval": -279
        },
        {
            "eval": -276
        },
        {
            "eval": -288
        },
        {
            "eval": -334
        },
        {
            "eval": 2,
            "best": "f8b8",
            "variation": "Rb8 Rd2",
            "judgment": {
                "name": "Blunder",
                "comment": "Blunder. Rb8 was best."
            }
        },
        {
            "eval": -24
        },
        {
            "eval": -31
        },
        {
            "eval": -82
        },
        {
            "eval": -69
        },
        {
            "eval": -222,
            "best": "d2d4",
            "variation": "Rd4 h5",
            "judgment": {
                "name": "Mistake",
                "comment": "Mistake. Rd4 was best."
            }
        },
        {
            "eval": -198
        },
        {
            "eval": -726,
            "best": "d2d3",
            "variation": "Rxd3 cxd3+ Rxd3 Kg8 Kd2 Kf7 b4 Re5 Kc2 Rh5 Bg1 Nd5 Kb3 Bf8",
            "judgment": {
                "name": "Blunder",
                "comment": "Blunder. Rxd3 was best."
            }
        },
        {
            "eval": -604
        },
        {
            "eval": -841,
            "best": "d2d3",
            "variation": "Rxd3 cxd3+ Rxd3 Nd5 Rxd5 Rxe3+ Kd1 Rxc3 Ra5 Rc6 b4 Bf4 a4 Bxh2",
            "judgment": {
                "name": "Inaccuracy",
                "comment": "Inaccuracy. Rxd3 was best."
            }
        },
        {
            "eval": -398,
            "best": "e8e3",
            "variation": "Rxe3+ Kf1 Rxf3+ Kg2 Ne1+ Rxe1 Bxd2 Re2 Rd3 c5 Bxc3 c6 Ba5 Re7",
            "judgment": {
                "name": "Mistake",
                "comment": "Mistake. Rxe3+ was best."
            }
        },
        {
            "eval": -369
        },
        {
            "eval": -363
        },
        {
            "eval": -398
        },
        {
            "eval": -382
        },
        {
            "eval": -798,
            "best": "d2d8",
            "variation": "Rd8 Nf4 Rxe8+ Nxe8 Rd8 Nh5+ Kg2 Nf6 Ra8 Kg7 Rxa6 Kf7 h4 Nc7",
            "judgment": {
                "name": "Mistake",
                "comment": "Mistake. Rd8 was best."
            }
        },
        {
            "eval": -614
        },
        {
            "eval": -846,
            "best": "d1e1",
            "variation": "Re1 Bf4+ Kxf4 Rxe1 Kxg5 Kg7 c5 Re5+ Kf4 Rxc5 Ke3 Rc4 Kd2 Ra4",
            "judgment": {
                "name": "Inaccuracy",
                "comment": "Inaccuracy. Re1 was best."
            }
        },
        {
            "eval": -758
        },
        {
            "eval": -750
        },
        {
            "eval": -715
        },
        {
            "eval": -812
        },
        {
            "eval": -752
        },
        {
            "mate": -1,
            "best": "g3h2",
            "variation": "Kh2 Nf7 Rd7 Kg8 Kg2 Bc5 Rf1 Ne5 Re1 a5 Rc7 Bf8 Ra7 Nf4+",
            "judgment": {
                "name": "Mistake",
                "comment": "Checkmate is now unavoidable. Kh2 was best."
            }
        }
    ],
    "clock": {
        "initial": 600,
        "increment": 0,
        "totalTime": 600
    }
}